Workbook

Sheet Extracted Data
A1: Reference No | B1: Date Submitted | C1: Company Name | D1: Contact Person | E1: Email | F1: Phone | G1: Category | H1: Payment Terms | I1: Annual Turnover (USD) | J1: Tax Registered | K1: Review Flag | L1: Source File
A2: VR-2026-101 | B2: 2026-06-21 | C2: Harbour Lane Supplies | D2: Amelia Hart | E2: amelia@harbourlanesup.example | F2: +27 51 254 7468 | G2: Office Supplies | H2: 30 days | I2: 880000 | J2: Yes | K2: OK | L2: vendor_form_01.pdf
A3: VR-2026-102 | B3: 2026-07-17 | C3: Bluegum Packaging | D3: Daniel Okafor | E3: daniel@bluegumpackagi.example | F3: +27 56 696 1950 | G3: Packaging | H3: 30 days | I3: 128000 | J3: No | K3: OK | L3: vendor_form_02.pdf
A4: VR-2026-103 | B4: 2026-09-03 | C4: Northfield Logistics | D4: Priya Nair | E4: priya@northfieldlogi.example | F4: +27 63 171 4943 | G4: Transport | H4: 30 days | I4: 886000 | J4: Yes | K4: OK | L4: vendor_form_03.pdf
A5: VR-2026-104 | B5: 2026-09-19 | C5: Kestrel Print Works | D5: Tom Becker | E5: tom@kestrelprintwo.example | F5: +27 38 745 2013 | G5: Printing | H5: 30 days | I5: 266000 | J5: Yes | K5: OK | L5: vendor_form_04.pdf
A6: VR-2026-105 | B6: 2026-09-10 | C6: Saltwater Catering Co | D6: Lerato Dube | E6: lerato@saltwatercater.example | F6: +27 81 979 3181 | G6: Catering | H6: 14 days | I6: 593000 | J6: Yes | K6: OK | L6: vendor_form_05.pdf
A7: VR-2026-106 | B7: 2026-07-04 | C7: Ironbark Tools | D7: Sofia Marino | E7: sofia@ironbarktools.example | F7: +27 83 415 3961 | G7: Hardware | H7: 60 days | I7: 139000 | J7: Yes | K7: OK | L7: vendor_form_06.pdf
A8: VR-2026-107 | B8: 2026-09-16 | C8: Maple & Finch Stationery | D8: James Whitlock | E8: james@maplefinchstat.example | F8: +27 82 161 4374 | G8: Office Supplies | H8: 60 days | I8: 516000 | J8: No | K8: OK | L8: vendor_form_07.pdf
A9: VR-2026-108 | B9: 2026-07-26 | C9: Redstone Electrical | D9: Hannah Kruger | E9: hannah@redstoneelectr.example | F9: +27 56 406 5070 | G9: Electrical | H9: 14 days | I9: 123000 | J9: No | K9: OK | L9: vendor_form_08.pdf
A10: VR-2026-109 | B10: 2026-09-24 | C10: Willowbrook Cleaning | D10: Marcus Lee | F10: +27 77 606 6627 | G10: Cleaning | H10: 60 days | I10: 663000 | J10: Yes | K10: Email missing | L10: vendor_form_09.pdf
A11: VR-2026-110 | B11: 2026-08-06 | C11: Summit Office Furniture | D11: Nomsa Zulu | E11: nomsa@summitofficefu.example | F11: +27 25 624 7850 | G11: Furniture | H11: 14 days | I11: 540000 | J11: No | K11: OK | L11: vendor_form_10.pdf
A12: VR-2026-111 | B12: 2026-08-25 | C12: Fernhill Fresh Produce | D12: Olivia Grant | E12: olivia@fernhillfreshp.example | F12: +27 15 784 2271 | G12: Catering | H12: 60 days | I12: 751000 | J12: No | K12: OK | L12: vendor_form_11.pdf
A13: VR-2026-112 | B13: 2026-06-03 | C13: Copperline Plumbing | D13: Peter Novak | E13: peter@copperlineplum.example | F13: +27 86 608 8474 | G13: Plumbing | H13: 60 days | I13: 525000 | J13: Yes | K13: OK | L13: vendor_form_12.pdf

Sheet Summary
A1: Extraction Summary
A2: Sample project - fictional data
A4: Forms processed | B4: =COUNTA('Extracted Data'!A2:A13) -> 12
A5: Clean records | B5: =COUNTIF('Extracted Data'!K2:K13,"OK") -> 11
A6: Records needing review | B6: =B4-B5 -> 1
A7: Total annual turnover (USD) | B7: =SUM('Extracted Data'!I2:I13) -> 6010000
A8: Average turnover (USD) | B8: =AVERAGE('Extracted Data'!I2:I13) -> 500833.33
A11: Vendors by category
A12: Category | B12: Vendors | C12: Turnover (USD)
A13: Catering | B13: =COUNTIF('Extracted Data'!G2:G13,A13) -> 2 | C13: =SUMIF('Extracted Data'!G2:G13,A13,'Extracted Data'!I2:I13) -> 1344000
A14: Cleaning | B14: =COUNTIF('Extracted Data'!G2:G13,A14) -> 1 | C14: =SUMIF('Extracted Data'!G2:G13,A14,'Extracted Data'!I2:I13) -> 663000
A15: Electrical | B15: =COUNTIF('Extracted Data'!G2:G13,A15) -> 1 | C15: =SUMIF('Extracted Data'!G2:G13,A15,'Extracted Data'!I2:I13) -> 123000
A16: Furniture | B16: =COUNTIF('Extracted Data'!G2:G13,A16) -> 1 | C16: =SUMIF('Extracted Data'!G2:G13,A16,'Extracted Data'!I2:I13) -> 540000
A17: Hardware | B17: =COUNTIF('Extracted Data'!G2:G13,A17) -> 1 | C17: =SUMIF('Extracted Data'!G2:G13,A17,'Extracted Data'!I2:I13) -> 139000
A18: Office Supplies | B18: =COUNTIF('Extracted Data'!G2:G13,A18) -> 2 | C18: =SUMIF('Extracted Data'!G2:G13,A18,'Extracted Data'!I2:I13) -> 1396000
A19: Packaging | B19: =COUNTIF('Extracted Data'!G2:G13,A19) -> 1 | C19: =SUMIF('Extracted Data'!G2:G13,A19,'Extracted Data'!I2:I13) -> 128000
A20: Plumbing | B20: =COUNTIF('Extracted Data'!G2:G13,A20) -> 1 | C20: =SUMIF('Extracted Data'!G2:G13,A20,'Extracted Data'!I2:I13) -> 525000
A21: Printing | B21: =COUNTIF('Extracted Data'!G2:G13,A21) -> 1 | C21: =SUMIF('Extracted Data'!G2:G13,A21,'Extracted Data'!I2:I13) -> 266000
A22: Transport | B22: =COUNTIF('Extracted Data'!G2:G13,A22) -> 1 | C22: =SUMIF('Extracted Data'!G2:G13,A22,'Extracted Data'!I2:I13) -> 886000
